odoo/addons/account_ecotax/README.rst
odoo/addons/account_ecotax/__init__.py
odoo/addons/account_ecotax/__manifest__.py
odoo/addons/account_ecotax/hook.py
odoo/addons/account_ecotax/data/decimal_precision.xml
odoo/addons/account_ecotax/i18n/account_ecotax.pot
odoo/addons/account_ecotax/i18n/fr.po
odoo/addons/account_ecotax/i18n/it.po
odoo/addons/account_ecotax/models/__init__.py
odoo/addons/account_ecotax/models/account_ecotax_category.py
odoo/addons/account_ecotax/models/account_ecotax_classification.py
odoo/addons/account_ecotax/models/account_move.py
odoo/addons/account_ecotax/models/account_move_line.py
odoo/addons/account_ecotax/models/account_move_line_ecotax.py
odoo/addons/account_ecotax/models/ecotax_collector.py
odoo/addons/account_ecotax/models/ecotax_line_mixin.py
odoo/addons/account_ecotax/models/ecotax_line_product.py
odoo/addons/account_ecotax/models/ecotax_sector.py
odoo/addons/account_ecotax/models/product_product.py
odoo/addons/account_ecotax/models/product_template.py
odoo/addons/account_ecotax/readme/CONTRIBUTORS.md
odoo/addons/account_ecotax/readme/DESCRIPTION.md
odoo/addons/account_ecotax/readme/USAGE.md
odoo/addons/account_ecotax/report/invoice.xml
odoo/addons/account_ecotax/security/ir.model.access.csv
odoo/addons/account_ecotax/security/ir_rule.xml
odoo/addons/account_ecotax/static/description/icon.png
odoo/addons/account_ecotax/static/description/index.html
odoo/addons/account_ecotax/tests/__init__.py
odoo/addons/account_ecotax/tests/test_ecotax.py
odoo/addons/account_ecotax/views/account_ecotax_category_view.xml
odoo/addons/account_ecotax/views/account_ecotax_classification_view.xml
odoo/addons/account_ecotax/views/account_ecotax_menu.xml
odoo/addons/account_ecotax/views/account_move_view.xml
odoo/addons/account_ecotax/views/ecotax_collector_view.xml
odoo/addons/account_ecotax/views/ecotax_sector_view.xml
odoo/addons/account_ecotax/views/product_template_view.xml
odoo/addons/account_ecotax/views/product_view.xml
odoo_addon_account_ecotax-18.0.1.0.0.8.dist-info/METADATA
odoo_addon_account_ecotax-18.0.1.0.0.8.dist-info/WHEEL
odoo_addon_account_ecotax-18.0.1.0.0.8.dist-info/top_level.txt
odoo_addon_account_ecotax-18.0.1.0.0.8.dist-info/RECORD
