Metadata-Version: 2.1
Name: odoo-addon-account_ecotax
Version: 18.0.1.0.0.8
Requires-Python: >=3.10
Requires-Dist: odoo==18.0.*
Summary: Ecotax Management: in French context is a 'cost' added to the sale price of electrical or electronic appliances or furnishing items
Home-page: https://github.com/OCA/account-fiscal-rule
License: AGPL-3
Author: Akretion, Odoo Community Association (OCA)
Author-email: support@odoo-community.org
Classifier: Programming Language :: Python
Classifier: Framework :: Odoo
Classifier: Framework :: Odoo :: 18.0
Classifier: License :: OSI Approved :: GNU Affero General Public License v3
